falcon_observability/Home.py
falcon_observability/__init__.py
falcon_observability/main.py
falcon_observability/pages/1_👨‍💻_Log_Monitor.py
falcon_observability/pages/2_📊_Log_Analytics.py
falcon_observability/static/AIAAS_FALCON.jpg
falcon_observability/utils/format.py
falcon_observability-0.1.0.dist-info/LICENSE
falcon_observability-0.1.0.dist-info/METADATA
falcon_observability-0.1.0.dist-info/WHEEL
falcon_observability-0.1.0.dist-info/RECORD
