Metadata-Version: 2.1
Name: falcon-observability
Version: 0.1.0
Summary: Falcon, a versatile and advanced platform, stands at the forefront of technological innovation, offering comprehensive support for Large Language Models (LLMs), audio processing, and beyond. It is expertly designed to cater to a wide array of needs, including training, inference, and meticulous monitoring, ensuring a seamless and efficient experience for users.
License: MIT
Author: Praveen Govindaraj
Author-email: praveengovi@gmil.com
Requires-Python: >=3.10,<4.0
Classifier: License :: OSI Approved :: MIT License
Classifier: Programming Language :: Python :: 3
Classifier: Programming Language :: Python :: 3.10
Classifier: Programming Language :: Python :: 3.11
Classifier: Programming Language :: Python :: 3.12
Requires-Dist: falcon-evaluate (>=0.1.9.2,<0.2.0.0)
Requires-Dist: gradio (>=4.7.1,<5.0.0)
Requires-Dist: streamlit-autorefresh (>=1.0.1,<2.0.0)
Requires-Dist: streamlit-extras (>=0.3.5,<0.4.0)
Requires-Dist: streamlit-monaco (>=0.1.3,<0.2.0)
